infi.systray-0.1.11-py2.7-nspkg.pth
infi/systray/__init__.py
infi/systray/__version__.py
infi/systray/traybar.py
infi/systray/win32_adapter.py
infi.systray-0.1.11.dist-info/DESCRIPTION.rst
infi.systray-0.1.11.dist-info/METADATA
infi.systray-0.1.11.dist-info/RECORD
infi.systray-0.1.11.dist-info/WHEEL
infi.systray-0.1.11.dist-info/entry_points.txt
infi.systray-0.1.11.dist-info/metadata.json
infi.systray-0.1.11.dist-info/namespace_packages.txt
infi.systray-0.1.11.dist-info/top_level.txt
